prioritydecorators/__init__.py
prioritydecorators/prioritydecorators.py
prioritydecorators-0.2.0.dist-info/LICENSE.txt
prioritydecorators-0.2.0.dist-info/METADATA
prioritydecorators-0.2.0.dist-info/WHEEL
prioritydecorators-0.2.0.dist-info/top_level.txt
prioritydecorators-0.2.0.dist-info/RECORD
