Metadata-Version: 2.1
Name: prioritydecorators
Version: 0.2.0
Summary: Library for adding/removing multiple decorators to a method with priorities
Home-page: UNKNOWN
Author: Maxim Gorbach
License: MIT
Platform: UNKNOWN
License-File: LICENSE.txt
Requires-Dist: sortedcontainers (==2.4.0)
